<?xml version="1.0" encoding="UTF-8"?>
<!DOCTYPE hibernate-mapping PUBLIC "-//Hibernate/Hibernate Mapping DTD 3.0//EN" "http://www.hibernate.org/dtd/hibernate-mapping-3.0.dtd">
<!-- Generated 21/06/2018 23:29:03 by Hibernate Tools 4.3.1 -->
<hibernate-mapping>
  <class catalog="cine" name="aplicacion.modelo.dominio.PelCla" optimistic-lock="version" table="pel_cla">
    <id name="pcCodigo" type="java.lang.Integer">
      <column name="pc_codigo"/>
      <generator class="identity"/>
    </id>
    <many-to-one class="aplicacion.modelo.dominio.Clasificacion" fetch="select" name="clasificaciones">
      <column name="pc_clasificacion" not-null="true"/>
    </many-to-one>
    <many-to-one class="aplicacion.modelo.dominio.Pelicula" fetch="select" name="peliculas">
      <column name="pc_pelicula" not-null="true"/>
    </many-to-one>
    <property name="pcEstado" type="boolean">
      <column name="pc_estado" not-null="true"/>
    </property>
  </class>
</hibernate-mapping>
